{
  "name": "vue-float-label",
  "full_name": "brtjkzl/vue-float-label",
  "description": "Float label pattern for Vue.js",
  "topics": [
    "vue",
    "vuejs",
    "float",
    "label"
  ],
  "license": {
    "key": "mit",
    "url": "https://api.github.com/licenses/mit",
    "name": "MIT License"
  },
  "owner": {
    "login": "brtjkzl",
    "avatar_url": "https://avatars3.githubusercontent.com/u/127219?v=4"
  },
  "organization": null,
  "links": {
    "site": null,
    "repo": "https://github.com/brtjkzl/vue-float-label"
  },
  "aliases": [],
  "colour": "#4FC08D"
}
