{
  "name": "vue-stepper",
  "full_name": "PygmySlowLoris/vue-stepper",
  "description": "A simple stepper with simple actions such as next, back and end to perform simple forms.",
  "topics": [],
  "license": {
    "key": "mit",
    "url": "https://api.github.com/licenses/mit",
    "name": "MIT License"
  },
  "owner": {
    "login": "PygmySlowLoris",
    "avatar_url": "https://avatars1.githubusercontent.com/u/27635664?v=4"
  },
  "organization": {
    "login": "PygmySlowLoris",
    "avatar_url": "https://avatars1.githubusercontent.com/u/27635664?v=4"
  },
  "links": {
    "site": null,
    "repo": "https://github.com/PygmySlowLoris/vue-stepper"
  },
  "aliases": [],
  "colour": "#4FC08D"
}
