{
  "name": "vuedals",
  "full_name": "javisperez/vuedals",
  "description": "Vue modals with a single component",
  "topics": [
    "vuejs",
    "vue",
    "modals",
    "bus",
    "window"
  ],
  "license": {
    "key": "mit",
    "url": "https://api.github.com/licenses/mit",
    "name": "MIT License"
  },
  "owner": {
    "login": "javisperez",
    "avatar_url": "https://avatars2.githubusercontent.com/u/4766570?v=4"
  },
  "organization": null,
  "links": {
    "site": null,
    "repo": "https://github.com/javisperez/vuedals"
  },
  "aliases": [],
  "colour": "#4FC08D"
}
